heter/__init__.py
heter/heter.py
heter-0.2.3.dist-info/METADATA
heter-0.2.3.dist-info/WHEEL
heter-0.2.3.dist-info/licenses/LICENSE
heter-0.2.3.dist-info/RECORD
