Metadata-Version: 2.4
Name: heter
Version: 0.2.3
Summary: Um buscador de arquivos recursivo, ultra-eficiente em memória usando geradores Python.
Project-URL: Homepage, https://github.com/S4muel-inz/Search-y
Author-email: Samuel Prevideli <samuelprevideli@gmail.com>
License: MIT
License-File: LICENSE
Keywords: files,generator,os.scandir,recursive,search
Classifier: License :: OSI Approved :: MIT License
Classifier: Operating System :: OS Independent
Classifier: Programming Language :: Python :: 3
Requires-Python: >=3.10
